mopidy_pidi/__init__.py
mopidy_pidi/brainz.py
mopidy_pidi/ext.conf
mopidy_pidi/frontend.py
mopidy_pidi/plugin.py
mopidy_pidi-1.0.4.dist-info/LICENSE
mopidy_pidi-1.0.4.dist-info/METADATA
mopidy_pidi-1.0.4.dist-info/WHEEL
mopidy_pidi-1.0.4.dist-info/entry_points.txt
mopidy_pidi-1.0.4.dist-info/top_level.txt
mopidy_pidi-1.0.4.dist-info/RECORD
